sphinx_fossasia_theme/__init__.py
sphinx_fossasia_theme/layout.html
sphinx_fossasia_theme/theme.conf
sphinx_fossasia_theme/static/fossasia.css_t
sphinx_fossasia_theme-0.0.4.dist-info/DESCRIPTION.rst
sphinx_fossasia_theme-0.0.4.dist-info/METADATA
sphinx_fossasia_theme-0.0.4.dist-info/RECORD
sphinx_fossasia_theme-0.0.4.dist-info/WHEEL
sphinx_fossasia_theme-0.0.4.dist-info/entry_points.txt
sphinx_fossasia_theme-0.0.4.dist-info/metadata.json
sphinx_fossasia_theme-0.0.4.dist-info/top_level.txt
